pyradiodns/__init__.py
pyradiodns/bearer.py
pyradiodns/rdns.py
pyradiodns/radiodns/__init__.py
pyradiodns/radiodns/am_service.py
pyradiodns/radiodns/dab_service.py
pyradiodns/radiodns/fm_service.py
pyradiodns/radiodns/hd_service.py
pyradiodns/radiodns/service.py
pyradiodns-0.2.dist-info/METADATA
pyradiodns-0.2.dist-info/WHEEL
pyradiodns-0.2.dist-info/top_level.txt
pyradiodns-0.2.dist-info/RECORD
